{
  "@type": "ListItem",
  "position": 181,
  "item": {
    "@type": "Article",
    "@id": "https://daniellehewych.org/archive/allwork-space/this-inexpensive-degree-could-kickstart-a-lucrativ",
    "name": "This Inexpensive Degree Could Kickstart A Lucrative Career",
    "url": "https://allwork.space/2022/07/this-inexpensive-degree-could-kickstart-a-lucrative-career/",
    "datePublished": "2022-07-27T00:00:00Z",
    "author": {
      "@type": "Person",
      "name": "Daniel Lehewych",
      "@id": "https://daniellehewych.org/#daniel-lehewych"
    }
  }
}