{
  "@type": "ListItem",
  "position": 358,
  "item": {
    "@type": "Article",
    "@id": "https://daniellehewych.org/archive/medium/the-mathematics-of-enlightenment",
    "name": "The Mathematics of Enlightenment",
    "url": "https://daniellehewych.medium.com/the-mathematics-of-enlightenment-cab788019a20",
    "datePublished": "2024-08-23T00:00:00Z",
    "author": {
      "@type": "Person",
      "name": "Daniel Lehewych",
      "@id": "https://daniellehewych.org/#daniel-lehewych"
    }
  }
}