{
  "@type": "ListItem",
  "position": 360,
  "item": {
    "@type": [
      "CriticalEssay",
      "ScholarlyArticle",
      "Article"
    ],
    "@id": "https://daniellehewych.org/archive/medium/deconstruction-and-its-problems-the-line-between-f",
    "name": "Deconstruction And Its Problems: The Line Between Freedom and Rigidity",
    "description": "Deconstruction And Its Problems: The Line Between Freedom and Rigidity",
    "url": "https://daniellehewych.medium.com/deconstruction-and-its-problems-the-line-between-freedom-and-rigidity-2e14048d3b11",
    "datePublished": "2019-11-28T00:00:00Z",
    "author": {
      "@id": "https://daniellehewych.org/#daniel-lehewych",
      "@type": "Person",
      "name": "Daniel Lehewych"
    },
    "isAccessibleForFree": true,
    "image": "https://images.squarespace-cdn.com/content/v1/5ff1bf1e8500a82fe9da19d6/e7b2be48-1fc7-4ff1-8d5b-15ff408f3502/image_123655411.jpg?format=1200w",
    "isPartOf": {
      "@type": [
        "Periodical",
        "CreativeWork"
      ],
      "name": "Medium",
      "issn": ""
    },
    "sameAs": [
      "https://daniellehewych.medium.com/deconstruction-and-its-problems-the-line-between-freedom-and-rigidity-2e14048d3b11",
      "https://daniellehewych.org/archive/medium/deconstruction-and-its-problems-the-line-between-f"
    ],
    "about": [
      {
        "@type": "Thing",
        "name": "Deconstruction"
      }
    ],
    "keywords": "Deconstruction",
    "genre": "Critical Essay",
    "educationalLevel": "Undergraduate",
    "usageInfo": {
      "@type": "CreativeWork",
      "@id": "https://daniellehewych.org/#ai-attribution-requirements"
    }
  }
}